hungtool/__init__.py
hungtool/lib2.py
hungtool-0.2.dist-info/METADATA
hungtool-0.2.dist-info/WHEEL
hungtool-0.2.dist-info/top_level.txt
hungtool-0.2.dist-info/RECORD
