Metadata-Version: 2.1
Name: hungtool
Version: 0.2
Summary: Taiwan No. 1
Home-page: http://github.com/storborg/hungtool
Author: Ming-Hung Hsu
Author-email: m870920@gmail.com
License: MIT
Platform: UNKNOWN
